LICENSE
MANIFEST.in
README.rst
requirements.txt
setup.cfg
setup.py
vvvv/__init__.py
vvvv/client.py
vvvv.egg-info/PKG-INFO
vvvv.egg-info/SOURCES.txt
vvvv.egg-info/dependency_links.txt
vvvv.egg-info/requires.txt
vvvv.egg-info/top_level.txt
vvvv.egg-info/zip-safe