Metadata-Version: 1.1
Name: vvvv
Version: 0.1.2
Summary: vvvv Python OSC client
Home-page: https://github.com/Djiit/vvvv
Author: Julien Tanay
Author-email: julien.tanay@gmail.com
License: Apache 2.0
Platform: UNKNOWN
Classifier: Development Status :: 3 - Alpha
Classifier: Intended Audience :: Developers
Classifier: License :: OSI Approved :: Apache Software License
Classifier: Programming Language :: Python :: 3
Classifier: Programming Language :: Python :: 3.3
Classifier: Programming Language :: Python :: 3.4
Classifier: Programming Language :: Python :: 3.5
